{
  "result": {
    "item": "openmodularturrets:expander",
    "data": 9
  },
  "pattern": [
    "ABA",
    "ECE",
    "ADA"
  ],
  "type": "forge:ore_shaped",
  "key": {
    "A": {
      "item": "#OBSIDIAN"
    },
    "B": {
      "item": "mekanism:energytablet",
      "data": 32767
    },
    "C": {
      "type": "forge:ore_dict",
      "ore": "blockRedstone"
    },
    "D": {
      "item": "#INGOTREFINEDOBSIDIAN"
    },
    "E": {
      "item": "#IOBUS"
    }
  },
  "conditions": [
    {
      "type": "openmodularturrets:recipetype",
      "mod": "mekanism"
    }
  ]
}
